assertions/__init__.py
pyssertions-0.0.1.dist-info/LICENSE
pyssertions-0.0.1.dist-info/WHEEL
pyssertions-0.0.1.dist-info/METADATA
pyssertions-0.0.1.dist-info/RECORD
